liyi_cute/__init__.py
liyi_cute/__main__.py
liyi_cute/processor/__init__.py
liyi_cute/processor/cut_sentence.py
liyi_cute/processor/data_augmentation.py
liyi_cute/processor/data_convert.py
liyi_cute/processor/data_output.py
liyi_cute/processor/process.py
liyi_cute/processor/tokenizers/__init__.py
liyi_cute/processor/tokenizers/sent_tokenizer.py
liyi_cute/processor/tokenizers/tokenizer_base.py
liyi_cute/processor/tokenizers/word_tokenizer.py
liyi_cute/processor/tokenizers/schemas/__init__.py
liyi_cute/processor/tokenizers/schemas/encoding.py
liyi_cute/shared/__init__.py
liyi_cute/shared/convert.py
liyi_cute/shared/exceptions.py
liyi_cute/shared/loadings.py
liyi_cute/shared/formats/__init__.py
liyi_cute/shared/formats/readerwriter.py
liyi_cute/shared/imports/__init__.py
liyi_cute/shared/imports/bart_parser.py
liyi_cute/shared/imports/base_parser.py
liyi_cute/shared/imports/conll_parser.py
liyi_cute/shared/imports/json_parser.py
liyi_cute/shared/imports/schemas/__init__.py
liyi_cute/shared/imports/schemas/schema.py
liyi_cute/shared/imports/schemas/schemaItem.py
liyi_cute/stat/__init__.py
liyi_cute/stat/statistics.py
liyi_cute/utils/__init__.py
liyi_cute/utils/common.py
liyi_cute/utils/constants.py
liyi_cute/utils/io.py
liyi_cute/utils/text_normalize.py
liyi_cute/vis/__init__.py
liyi_cute/vis/visualization.py
liyi_cute-0.0.6.dist-info/LICENSE
liyi_cute-0.0.6.dist-info/METADATA
liyi_cute-0.0.6.dist-info/WHEEL
liyi_cute-0.0.6.dist-info/entry_points.txt
liyi_cute-0.0.6.dist-info/top_level.txt
liyi_cute-0.0.6.dist-info/RECORD
