Metadata-Version: 2.1
Name: liyi-cute
Version: 0.0.6
Summary: A text processing tools
Home-page: https://github.com/daiyizheng/liyi-cute
Author: yizheng dai
Author-email: 387942239@qq.com
Maintainer: yizheng dai
Maintainer-email: 387942239@qq.com
License: Apache 2.0
Project-URL: Bug Reports, https://github.com/daiyizheng/liyi-cute/issues
Project-URL: Source, https://github.com/daiyizheng/liyi-cute
Keywords: Text processing tools,including named entity recognition,relation extraction,event extraction,and some statistical and visualization functions
Classifier: Intended Audience :: Developers
Classifier: License :: OSI Approved :: Apache Software License
Classifier: Programming Language :: Python
Classifier: Programming Language :: Python :: 3.7
Classifier: Programming Language :: Python :: 3.8
Classifier: Topic :: Software Development
Requires-Python: >=3.7
License-File: LICENSE
Requires-Dist: marshmallow (>=3.15.0)
